habitat_tools/__init__.py
habitat_tools/api_tools.py
habitat_tools/exceptions.py
habitat_tools/utils.py
habitat_tools-0.1.14.dist-info/WHEEL
habitat_tools-0.1.14.dist-info/METADATA
habitat_tools-0.1.14.dist-info/RECORD
